libertem_ui/__init__.py
libertem_ui/__version__.py
libertem_ui/api.py
libertem_ui/base.py
libertem_ui/figure.py
libertem_ui/lifecycles.py
libertem_ui/live_plot.py
libertem_ui/resources.py
libertem_ui/ui_context.py
libertem_ui/_static/lt_icon.svg
libertem_ui/_static/lt_logo.svg
libertem_ui/applications/__init__.py
libertem_ui/applications/file_browser.py
libertem_ui/applications/image_transformer.py
libertem_ui/applications/image_utils.py
libertem_ui/applications/line_profile.py
libertem_ui/applications/load_dataset.py
libertem_ui/applications/terminal_logger.py
libertem_ui/display/display_base.py
libertem_ui/display/gamma_mapper.ts
libertem_ui/display/image_datashader.py
libertem_ui/display/image_db.py
libertem_ui/display/lattice.py
libertem_ui/display/vectors.py
libertem_ui/display/icons/LineEdit.png
libertem_ui/display/icons/__init__.py
libertem_ui/display/icons/cursor.png
libertem_ui/display/icons/cursor.svg
libertem_ui/display/icons/freedraw.png
libertem_ui/display/icons/freedraw.svg
libertem_ui/display/icons/freepoint.png
libertem_ui/display/icons/freepoint.svg
libertem_ui/display/icons/options.png
libertem_ui/display/icons/options.svg
libertem_ui/display/icons/options_blue.png
libertem_ui/display/icons/options_blue.svg
libertem_ui/display/icons/sigma.png
libertem_ui/display/icons/sigma.svg
libertem_ui/display/icons/xselect.png
libertem_ui/display/icons/xselect.svg
libertem_ui/display/icons/yselect.png
libertem_ui/display/icons/yselect.svg
libertem_ui/results/__init__.py
libertem_ui/results/containers.py
libertem_ui/results/results_manager.py
libertem_ui/results/tracker.py
libertem_ui/utils/__init__.py
libertem_ui/utils/colormaps.py
libertem_ui/utils/data.py
libertem_ui/utils/export.py
libertem_ui/utils/logging.py
libertem_ui/utils/notebook_tools.py
libertem_ui/utils/panel_components.py
libertem_ui/utils/param_converters.py
libertem_ui/utils/progress.py
libertem_ui/windows/__init__.py
libertem_ui/windows/base.py
libertem_ui/windows/com.py
libertem_ui-0.0.1.dist-info/METADATA
libertem_ui-0.0.1.dist-info/WHEEL
libertem_ui-0.0.1.dist-info/licenses/LICENSE
libertem_ui-0.0.1.dist-info/RECORD
