Metadata-Version: 2.4
Name: libertem-ui
Version: 0.0.1
Summary: Panel+Bokeh-based GUI Toolkit for LiberTEM
Project-URL: Repository, https://github.com/LiberTEM/LiberTEM-panel-ui
Author-email: the LiberTEM team <libertem-dev@googlegroups.com>
License: Copyright (c) 2022- Matthew Bryan and others
License-File: LICENSE
Keywords: electron,gui,microscopy,notebook
Classifier: Development Status :: 3 - Alpha
Classifier: Environment :: Console
Classifier: Environment :: Web Environment
Classifier: License :: OSI Approved :: MIT License
Classifier: Operating System :: MacOS :: MacOS X
Classifier: Operating System :: Microsoft :: Windows
Classifier: Operating System :: POSIX :: Linux
Classifier: Programming Language :: Python :: 3
Classifier: Programming Language :: Python :: 3.10
Classifier: Programming Language :: Python :: 3.11
Classifier: Programming Language :: Python :: 3.12
Classifier: Programming Language :: Python :: 3.13
Requires-Python: >=3.10
Requires-Dist: bidict
Requires-Dist: bokeh>=3.4.0
Requires-Dist: colorcet
Requires-Dist: datashader
Requires-Dist: humanize
Requires-Dist: numba
Requires-Dist: numpy
Requires-Dist: pandas
Requires-Dist: panel>=1
Requires-Dist: scikit-image
Requires-Dist: scipy
Requires-Dist: strenum
Requires-Dist: tifffile
Requires-Dist: typing-extensions
Requires-Dist: xarray
Provides-Extra: libertem
Requires-Dist: libertem; extra == 'libertem'
Requires-Dist: libertem-live; extra == 'libertem'
Provides-Extra: notebook
Requires-Dist: ipython; extra == 'notebook'
Requires-Dist: ipywidgets; extra == 'notebook'
Requires-Dist: jupyter-bokeh; extra == 'notebook'
Requires-Dist: notebook; extra == 'notebook'
